LICENSE
README.md
setup.py
DataGenerator/__init__.py
DataGenerator/Attribute/CaseAttribute.c
DataGenerator/Attribute/CaseAttribute.pyx
DataGenerator/Attribute/IsAdjectiveAttribute.c
DataGenerator/Attribute/IsAdjectiveAttribute.pyx
DataGenerator/Attribute/IsAuxiliaryVerbAttribute.c
DataGenerator/Attribute/IsAuxiliaryVerbAttribute.pyx
DataGenerator/Attribute/IsCapitalAttribute.c
DataGenerator/Attribute/IsCapitalAttribute.pyx
DataGenerator/Attribute/IsDateAttribute.c
DataGenerator/Attribute/IsDateAttribute.pyx
DataGenerator/Attribute/IsFractionAttribute.c
DataGenerator/Attribute/IsFractionAttribute.pyx
DataGenerator/Attribute/IsHonorificAttribute.c
DataGenerator/Attribute/IsHonorificAttribute.pyx
DataGenerator/Attribute/IsLocationGazetteer.c
DataGenerator/Attribute/IsLocationGazetteer.pyx
DataGenerator/Attribute/IsMoneyAttribute.c
DataGenerator/Attribute/IsMoneyAttribute.pyx
DataGenerator/Attribute/IsNumberAttribute.c
DataGenerator/Attribute/IsNumberAttribute.pyx
DataGenerator/Attribute/IsOrganizationAttribute.c
DataGenerator/Attribute/IsOrganizationAttribute.pyx
DataGenerator/Attribute/IsOrganizationGazetteer.c
DataGenerator/Attribute/IsOrganizationGazetteer.pyx
DataGenerator/Attribute/IsPersonGazetteer.c
DataGenerator/Attribute/IsPersonGazetteer.pyx
DataGenerator/Attribute/IsProperNounAttribute.c
DataGenerator/Attribute/IsProperNounAttribute.pyx
DataGenerator/Attribute/IsRealAttribute.c
DataGenerator/Attribute/IsRealAttribute.pyx
DataGenerator/Attribute/IsTimeAttribute.c
DataGenerator/Attribute/IsTimeAttribute.pyx
DataGenerator/Attribute/LastIGContainsPossessiveAttribute.c
DataGenerator/Attribute/LastIGContainsPossessiveAttribute.pyx
DataGenerator/Attribute/LastIGContainsTagAblativeAttribute.c
DataGenerator/Attribute/LastIGContainsTagAblativeAttribute.pyx
DataGenerator/Attribute/LastIGContainsTagAccusativeAttribute.c
DataGenerator/Attribute/LastIGContainsTagAccusativeAttribute.pyx
DataGenerator/Attribute/LastIGContainsTagAttribute.c
NlpToolkit_DataGenerator_Cy.egg-info/PKG-INFO
NlpToolkit_DataGenerator_Cy.egg-info/SOURCES.txt
NlpToolkit_DataGenerator_Cy.egg-info/dependency_links.txt
NlpToolkit_DataGenerator_Cy.egg-info/requires.txt
NlpToolkit_DataGenerator_Cy.egg-info/top_level.txt
nlptoolkit_datagenerator_cy.egg-info/PKG-INFO
nlptoolkit_datagenerator_cy.egg-info/SOURCES.txt
nlptoolkit_datagenerator_cy.egg-info/dependency_links.txt
nlptoolkit_datagenerator_cy.egg-info/requires.txt
nlptoolkit_datagenerator_cy.egg-info/top_level.txt