Metadata-Version: 2.4
Name: nlptoolkit-datagenerator-cy
Version: 1.0.4
Summary: Classification dataset generator library for high level Nlp tasks
Home-page: https://github.com/StarlangSoftware/DataGenerator-Cy
Author: olcaytaner
Author-email: olcay.yildiz@ozyegin.edu.tr
License-File: LICENSE
Requires-Dist: NlpToolkit-AnnotatedTree-Cy
Requires-Dist: NlpToolkit-Classification-Cy
Requires-Dist: NlpToolkit-MorphologicalDisambiguation-Cy
Dynamic: author
Dynamic: author-email
Dynamic: description
Dynamic: description-content-type
Dynamic: home-page
Dynamic: license-file
Dynamic: requires-dist
Dynamic: summary
